nett/__init__.py
nett/nett.py
nett/body/__init__.py
nett/body/builder.py
nett/brain/__init__.py
nett/brain/builder.py
nett/brain/encoders/__init__.py
nett/brain/encoders/cnnlstm.py
nett/brain/encoders/cotracker.py
nett/brain/encoders/dinov1.py
nett/brain/encoders/dinov2.py
nett/brain/encoders/resnet18.py
nett/brain/encoders/rnd.py
nett/brain/encoders/sam.py
nett/brain/encoders/vit.py
nett/environment/__init__.py
nett/environment/builder.py
nett/environment/configs.py
nett/utils/__init__.py
nett/utils/callbacks.py
nett/utils/environment.py
nett/utils/gpu.py
nett/utils/io.py
nett/utils/logger.py
nett/utils/train.py
nett/utils/validation.py
nett/utils/visualization.py
nett_benchmarks-0.15.dist-info/LICENSE
nett_benchmarks-0.15.dist-info/METADATA
nett_benchmarks-0.15.dist-info/WHEEL
nett_benchmarks-0.15.dist-info/top_level.txt
nett_benchmarks-0.15.dist-info/RECORD
