Metadata-Version: 2.1
Name: nett-benchmarks
Version: 0.15
Summary: A testbed for comparing the learning abilities of newborn animals and autonomous artificial agents.
Author-email: Bhargav Desai <desabh@iu.edu>
Project-URL: Homepage, https://github.com/pypa/sampleproject
Project-URL: Bug Tracker, https://github.com/pypa/sampleproject/issues
Requires-Python: <3.10.13,>=3.10.12
License-File: LICENSE
Requires-Dist: mlagents ==1.0.0
Requires-Dist: stable-baselines3[extra] ==1.8.0
Requires-Dist: sb3-contrib ==1.8.0
Requires-Dist: imageio-ffmpeg
Requires-Dist: torchvision
Requires-Dist: scipy
Requires-Dist: timm
Requires-Dist: nvidia-ml-py
Requires-Dist: ipywidgets
